vamos/__init__.py
vamos-0.1.0.dist-info/METADATA
vamos-0.1.0.dist-info/WHEEL
vamos-0.1.0.dist-info/RECORD
