Metadata-Version: 2.1
Name: vamos
Version: 0.1.0
Summary: 
Author: ihux
Author-email: hugo.pristauz@gmail.com
Requires-Python: >=3.11,<4.0
Classifier: Programming Language :: Python :: 3
Classifier: Programming Language :: Python :: 3.11
Classifier: Programming Language :: Python :: 3.12
Requires-Dist: colorama (>=0.4.6,<0.5.0)
Requires-Dist: shellingham (>=1.5.4,<2.0.0)
Requires-Dist: typer (>=0.9.0,<0.10.0)
